topsis_aryan/__init__.py
topsis_aryan/run_topsis.py
topsis_aryansaini_102303666-1.0.0.dist-info/licenses/LICENSE.txt
topsis_aryansaini_102303666-1.0.0.dist-info/METADATA
topsis_aryansaini_102303666-1.0.0.dist-info/WHEEL
topsis_aryansaini_102303666-1.0.0.dist-info/entry_points.txt
topsis_aryansaini_102303666-1.0.0.dist-info/top_level.txt
topsis_aryansaini_102303666-1.0.0.dist-info/RECORD
