Metadata-Version: 2.4
Name: Topsis-AryanSaini-102303666
Version: 1.0.0
Summary: A Python package for TOPSIS (Technique for Order of Preference by Similarity to Ideal Solution)
Author: Aryan
Author-email: asaini2_be23@thapar.edu
Classifier: Programming Language :: Python :: 3
Classifier: License :: OSI Approved :: MIT License
Classifier: Operating System :: OS Independent
Requires-Python: >=3.6
License-File: LICENSE.txt
Requires-Dist: pandas
Dynamic: author
Dynamic: author-email
Dynamic: classifier
Dynamic: description
Dynamic: description-content-type
Dynamic: license-file
Dynamic: requires-dist
Dynamic: requires-python
Dynamic: summary
